{"index.md":"CIytJBsd","interview_1.frontend-interview-html_02. 语义化_语义化.md":"CH9NMN2S","interview_1.frontend-interview-html_07. 替换元素_替换元素.md":"B3wFHH5N","interview_1.frontend-interview-html_04. seo_seo.md":"YC_b2Iwo","interview_1.frontend-interview-html_03. w3c标准组织_w3c 标准组织.md":"IwFtow84","interview_1.frontend-interview-html_08. 页面可见性_页面可见性.md":"R5G9WJkP","interview_1.frontend-interview-html_01. 文档声明_文档声明.md":"1WCTi2g4","interview_2.frontend-interview-css_01. css单位总结_css单位总结.md":"JjedV0h6","interview_1.frontend-interview-html_06. 微格式_微格式.md":"DuI9-LIc","interview_1.frontend-interview-html_html 面试题汇总（无答案版）.md":"DUViUd9d","interview_1.frontend-interview-html_05. iframe_iframe.md":"Bh1pEqYn","interview_2.frontend-interview-css_03. 隐藏元素的方式总结_隐藏元素的方式总结.md":"BjD-U8bk","interview_2.frontend-interview-css_02. 居中方式总结_居中方式总结.md":"I4b0BYeN","interview_2.frontend-interview-css_07. css属性的计算过程_css属性的计算过程.md":"C11RxOQg","interview_2.frontend-interview-css_05. 定位总结_定位总结.md":"C0RDFdOl","interview_2.frontend-interview-css_04. 浮动_浮动.md":"p9EatCtq","interview_2.frontend-interview-css_10. css3的calc函数_css3的calc函数.md":"DLjf4rVJ","interview_2.frontend-interview-css_06. bfc_bfc.md":"RqU7wcLO","interview_2.frontend-interview-css_08. css层叠继承规则总结_css层叠继承规则总结.md":"C09v3G1J","interview_2.frontend-interview-css_09. import指令_import指令.md":"BDVjwm--","interview_2.frontend-interview-css_15. 渐进式渲染_渐进式渲染.md":"CKlUs_OO","interview_2.frontend-interview-css_12. 过渡和动画事件_过渡和动画事件.md":"zYsGtkS6","interview_2.frontend-interview-css_16. css渲染性能优化_css渲染性能优化.md":"CjQJWOc4","interview_2.frontend-interview-css_11. css3的媒介(media)查询_css3的媒介(media)查询.md":"CX_RUE3D","interview_2.frontend-interview-css_13. 渐进增强和优雅降级_渐进增强和优雅降级.md":"DILYo9Ki","interview_2.frontend-interview-css_18. css3 遮罩_css3 遮罩.md":"teQt7Rcz","interview_2.frontend-interview-css_css 面试题汇总（无答案版）.md":"B-dA8FqX","interview_3.frontend-interview-javascript_02. 值和引用_值和引用.md":"BnwHPqsZ","interview_3.frontend-interview-javascript_01. let、var、const的区别_let、var、const的区别.md":"CmJ0977K","interview_2.frontend-interview-css_17. 堆叠上下文_层叠上下文.md":"YKxxA41S","interview_2.frontend-interview-css_14. css3变形_css3 变形.md":"D0gbbJcm","interview_3.frontend-interview-javascript_03. 包装类型_包装类型.md":"DGnh0m_V","interview_3.frontend-interview-javascript_04. 数据类型的转换_数据类型的转换.md":"DfECeEBL","interview_3.frontend-interview-javascript_07. 执行栈和执行上下文_执行栈和执行上下文.md":"BG490swp","interview_3.frontend-interview-javascript_08. 作用域和作用域链_作用域和作用域链.md":"YkrDTdCA","interview_3.frontend-interview-javascript_06. 原型和原型链_原型和原型链.md":"JvH6zx2v","interview_3.frontend-interview-javascript_10. 垃圾回收与内存泄漏_垃圾回收与内存泄漏.md":"B0TSRWiT","interview_3.frontend-interview-javascript_05. 运算符_运算符.md":"DE9-4IeQ","interview_3.frontend-interview-javascript_12. dom事件的注册和移除_dom 事件的注册和移除.md":"Jfe_kEIC","interview_3.frontend-interview-javascript_14. 阻止事件的默认行为_阻止事件默认行为.md":"BjuJ4VM5","interview_3.frontend-interview-javascript_15. 递归_递归.md":"DRDZnf0g","interview_3.frontend-interview-javascript_11. 闭包_闭包.md":"DoN6iAvA","interview_3.frontend-interview-javascript_13. dom事件的传播机制_dom 事件的传播机制.md":"DwWoDA-a","interview_3.frontend-interview-javascript_18. 浮点数精度问题_浮点数精度问题.md":"weRB7clF","interview_3.frontend-interview-javascript_19. 严格模式_严格模式.md":"BpRZ88Nj","interview_3.frontend-interview-javascript_16. 属性描述符_属性描述符.md":"6SLUYHm2","interview_3.frontend-interview-javascript_09. this指向_this指向.md":"D3AoYQ5A","interview_3.frontend-interview-javascript_20. 函数防抖和节流_函数防抖和节流.md":"DAjNkzYD","interview_3.frontend-interview-javascript_17. class和普通构造器的区别_class 和构造函数区别.md":"BUE0kIVu","interview_3.frontend-interview-javascript_25. eval_eval.md":"BssPHj7K","interview_3.frontend-interview-javascript_27. 更多知识_更多知识.md":"CFP_2GlF","interview_3.frontend-interview-javascript_21. weakset和weakmap_weakset 和 weakmap.md":"CKs_RSLz","interview_3.frontend-interview-javascript_24. node的事件循环_node的事件循环.md":"D98slQCu","interview_3.frontend-interview-javascript_22. 深浅拷贝_深浅拷贝.md":"_oHPd7_e","interview_3.frontend-interview-javascript_23. 函数柯里化_函数柯里化.md":"u953Fv61","interview_3.frontend-interview-javascript_26. 尺寸和位置_尺寸和位置.md":"fAjYy4TI","interview_4.frontend-interview-promise_01. promise基础_笔记.md":"CBhc0GsU","interview_4.frontend-interview-promise_06. 手写promise_说明.md":"BxxMC9eG","interview_4.frontend-interview-promise_04. async和await_笔记.md":"CvosEICB","interview_5.frontend-interview-browser_03. 浏览器的组成部分_浏览器的组成部分.md":"kfoOB1q8","interview_4.frontend-interview-promise_03. promise的静态方法_笔记.md":"DYvXReiR","interview_4.frontend-interview-promise_02. promise的链式调用_笔记.md":"DkUJKqVp","interview_4.frontend-interview-promise_promise面试题归总（无答案版）.md":"OpQXejC4","interview_5.frontend-interview-browser_04. 浏览器的离线存储概述_浏览器离线存储概述.md":"BCfKLVYk","interview_5.frontend-interview-browser_01. 浏览器的渲染流程_浏览器的渲染流程.md":"63eKXxTF","interview_5.frontend-interview-browser_02. 资源提示关键词_资源提示关键词.md":"CKznrU0_","interview_5.frontend-interview-browser_05. websql_websql.md":"223hkBrn","interview_4.frontend-interview-promise_05. promise相关面试题_笔记.md":"Clpt4PvR","interview_5.frontend-interview-browser_08. 浏览器的缓存_浏览器缓存.md":"4lRdJnp4","interview_5.frontend-interview-browser_07. file api_file api.md":"CB7vK7Af","interview_6.frontend-interview-network_03. cookie_课件.md":"CbcoWmSd","interview_6.frontend-interview-network_01. 五层网络模型_课件.md":"wtErPXHy","interview_6.frontend-interview-network_08. 跨域-代理_课件.md":"eJIbxZui","interview_5.frontend-interview-browser_浏览器面试题汇总（无答案版）.md":"Y0B-0wn-","interview_6.frontend-interview-network_04. cookie和strorage_课件.md":"7Eg1aubG","interview_6.frontend-interview-network_05. 加密_课件.md":"Cb3RRUHU","interview_6.frontend-interview-network_07. 同源策略_课件.md":"BIQ0SWn2","interview_6.frontend-interview-network_02. 常见请求方法_课件.md":"BNl0dvcY","interview_6.frontend-interview-network_06. jwt_课件.md":"Ckf8SAf2","interview_5.frontend-interview-browser_18. web worker_web worker.md":"52QeTRml","interview_5.frontend-interview-browser_06. indexeddb_indexeddb.md":"D_GuW_RN","interview_3.frontend-interview-javascript_javascript 面试题汇总（无答案）.md":"Doi4wcME","interview_6.frontend-interview-network_14. session_课件.md":"Bz2JOCDf","interview_6.frontend-interview-network_22. ssl、tls、https_课件.md":"B2JhiNRw","interview_6.frontend-interview-network_18. xss攻击_课件.md":"DhnBjUZb","interview_6.frontend-interview-network_10. 跨域-jsonp_课件.md":"CtHWCpBN","interview_6.frontend-interview-network_09. 跨域-cors_课件.md":"DhZghrZ7","interview_6.frontend-interview-network_11. 文件上传_后端服务器_public_upload_readme.md":"X09EkBCZ","interview_6.frontend-interview-network_17. csrf攻击_课件.md":"BeQ9YhOA","interview_6.frontend-interview-network_12. 输入url地址后_课件.md":"BLDuPggD","interview_6.frontend-interview-network_19. 网络性能优化_课件.md":"BbC2Damv","interview_6.frontend-interview-network_23. http各版本差异_课件.md":"BoS8qvEX","interview_6.frontend-interview-network_13. 文件下载_课件.md":"DPq21NoN","interview_7.frontend-interview-engineering_05. webpack scope hoisting_课件.md":"lLOvyp0-","interview_7.frontend-interview-engineering_02. npx_课件.md":"C2IVV0vs","interview_7.frontend-interview-engineering_04. 关于webpack的诸多问题_课件.md":"DwG1j_Zs","interview_7.frontend-interview-engineering_06. webpack5更新了什么_课件.md":"Bn_4VKlu","interview_6.frontend-interview-network_11. 文件上传_课件.md":"CoqYywnp","interview_6.frontend-interview-network_21. 域名和dns_课件.md":"E34hZuMR","interview_6.frontend-interview-network_25. websocket实战_client_readme.md":"Brshi7xi","interview_6.frontend-interview-network_25. websocket实战_课件.md":"zMrFt709","interview_6.frontend-interview-network_网络面试题汇总（无答案版）.md":"CT_UrBoZ","interview_7.frontend-interview-engineering_03. eslint_课件.md":"BBdtWigY","interview_6.frontend-interview-network_16. tcp协议_课件.md":"8PFX4r8d","interview_6.frontend-interview-network_15. http缓存协议_课件.md":"CWlmUArf","interview_6.frontend-interview-network_20. 断点续传_课件.md":"CRK0T-1m","interview_7.frontend-interview-engineering_03. eslint_vue-app_readme.md":"Qzudy8S-","interview_7.frontend-interview-engineering_01. cmj和esm_课件.md":"CcYwJAUI","interview_7.frontend-interview-engineering_07. npm模块安装机制_课件.md":"5-C26zze","interview_8.frontend-interview-vue_01. 组件通信总结_demo_readme.md":"Bo044gdo","interview_7.frontend-interview-engineering_工程化面试题汇总（无答案版）.md":"CcMaH5Xp","interview_6.frontend-interview-network_24. websocket_课件.md":"CsTVm0eB","interview_6.frontend-interview-network_25. websocket实战_chat-room_readme.md":"Czr1FZDP","interview_8.frontend-interview-vue_02. 虚拟dom详解_课堂代码_demo_readme.md":"6jXAYm5G","interview_8.frontend-interview-vue_02. 虚拟dom详解_课件_笔记.md":"CFUJi1Mf","interview_8.frontend-interview-vue_10. 过渡和动画_课件_笔记.md":"DXsSgwwc","interview_8.frontend-interview-vue_10. 过渡和动画_课件_demo2_readme.md":"CCvQo4LE","interview_8.frontend-interview-vue_07. 你不知道的computed_课件_笔记.md":"BvZZfrB1","interview_8.frontend-interview-vue_11. 优化_课堂代码_4. 保持对象引用稳定_readme.md":"CZJO3K-7","interview_8.frontend-interview-vue_09. 作用域插槽_课堂代码_demo_readme.md":"DqhvJQmW","interview_8.frontend-interview-vue_10. 过渡和动画_课堂代码_demo2_readme.md":"CwsaFICc","interview_8.frontend-interview-vue_11. 优化_课堂代码_5. 延迟装载_readme.md":"zc9ZHvCG","interview_8.frontend-interview-vue_11. 优化_课堂代码_2. 使用函数式组件_readme.md":"D-Lu6z4R","interview_8.frontend-interview-vue_11. 优化_课堂代码_1. 使用冻结对象_readme.md":"vgwTeHpu","interview_8.frontend-interview-vue_12. keep-alive_课堂代码_demo1_readme.md":"DUoX5a1K","interview_8.frontend-interview-vue_19. 路由切换动画_课件_demo_readme.md":"CETdY0wx","interview_8.frontend-interview-vue_08. filter过滤器_课件_笔记.md":"BAxtz-4a","interview_8.frontend-interview-vue_06. 生命周期详解_课件_笔记.md":"CHxl8dbO","interview_8.frontend-interview-vue_09. 作用域插槽_课件_笔记.md":"MuhBwSdx","interview_8.frontend-interview-vue_15. 模式和环境变量_课堂代码_demo_readme.md":"WBPB3Mxy","interview_8.frontend-interview-vue_11. 优化_课堂代码_3. 非实时绑定的表单项_readme.md":"CgKt2G23","interview_8.frontend-interview-vue_06. 生命周期详解_课堂代码_demo_readme.md":"Bu4lGf1i","interview_8.frontend-interview-vue_19. 路由切换动画_课堂代码_demo_readme.md":"BbwfQWOO","interview_8.frontend-interview-vue_16. 更多配置_课件_笔记.md":"BNJAkSfm","interview_8.frontend-interview-vue_说明（必看）.md":"B2OBnYlY","interview_8.frontend-interview-vue_17. 更多命令_课堂代码_demo_readme.md":"DchhVfLt","interview_8.frontend-interview-vue_03. v-model_课堂代码_demo_readme.md":"DHYX9Gw4","interview_8.frontend-interview-vue_05. diff_课件_笔记.md":"BJ4p7wg_","interview_8.frontend-interview-vue_10. 过渡和动画_课件_demo1_readme.md":"Bw2VkZGE","interview_8.frontend-interview-vue_03. v-model_课件_笔记.md":"9tAxiB1H","interview_8.frontend-interview-vue_04. 数据响应原理_课件_笔记.md":"Bouej8Ma","interview_8.frontend-interview-vue_10. 过渡和动画_课堂代码_demo_readme.md":"Cm5itQtF","interview_8.frontend-interview-vue_16. 更多配置_课堂代码_my-site_readme.md":"D1wQpO2v","interview_8.frontend-interview-vue_12. keep-alive_课件_笔记.md":"bCwXgkEx","interview_8.frontend-interview-vue_15. 模式和环境变量_课件_笔记.md":"CnKLoGHr","interview_7.frontend-interview-engineering_08. 模块联邦_课件.md":"CbVXZULs","interview_8.frontend-interview-vue_10. 过渡和动画_课堂代码_demo1_readme.md":"BwtaA-TR","interview_8.frontend-interview-vue_08. filter过滤器_课堂代码_demo_readme.md":"1SB-Q-C-","interview_8.frontend-interview-vue_16. 更多配置_课堂代码_my-site_src_components_readme.md":"D_NHFsdp","interview_8.frontend-interview-vue_11. 优化_课件_笔记.md":"CSanNLHi","interview_8.frontend-interview-vue_12. keep-alive_课堂代码_demo2_readme.md":"Bn8E4dB1","interview_8.frontend-interview-vue_13. 长列表优化_课件_课件.md":"9jM30Ad3","interview_8.frontend-interview-vue_vue笔面试题汇总（无答案版）.md":"Dgs0b98N","interview_8.frontend-interview-vue_14. 其他api_课堂代码_demo_readme.md":"BQKaGi31","interview_8.frontend-interview-vue_13. 长列表优化_课堂代码_demo_readme.md":"_OB8gsxx","interview_8.frontend-interview-vue_18. 嵌套路由_课堂代码_demo_readme.md":"CdRN2bsy","interview_8.frontend-interview-vue_01. 组件通信总结_课件_笔记.md":"CnLelAhn","interview_5.frontend-interview-browser_09. 跨标签页通信概述_跨标签页通信.md":"Df997__1"}
